tests/__init__.py
uniqcharstest2-1.0.dist-info/LICENSE
uniqcharstest2-1.0.dist-info/METADATA
uniqcharstest2-1.0.dist-info/WHEEL
uniqcharstest2-1.0.dist-info/entry_points.txt
uniqcharstest2-1.0.dist-info/top_level.txt
uniqcharstest2-1.0.dist-info/RECORD
